{
    "dataset": "set_nopts5_ncomb1_nproblem50_no5.mat",
    "nsamples": 150,
    "ntest": 10000,
    "results": [
        {
            "M": [
                [
                    0.6022964715957642,
                    6.811217308044434
                ],
                [
                    5.000604629516602,
                    7.0901923179626465
                ],
                [
                    5.3357062339782715,
                    5.947579383850098
                ],
                [
                    4.626784801483154,
                    2.6624560356140137
                ],
                [
                    4.134827613830566,
                    3.339236259460449
                ]
            ],
            "actual_freq": [
                [
                    0.0001,
                    0.996,
                    0.0,
                    0.0039,
                    0.0
                ]
            ],
            "avg_t": 25.0,
            "b": 6.0,
            "freq": [
                [
                    0.0,
                    0.9931,
                    0.0,
                    0.006,
                    0.0009
                ]
            ],
            "iter": 35,
            "mse": 1.364000000000008e-05,
            "phi1": 0.06636687368154526,
            "phi2": 0.04634837806224823,
            "sig2": 0.8370958472757661,
            "threshold": 25,
            "time": 1.5696868896484375,
            "w": [
                [
                    0.3
                ],
                [
                    0.7
                ]
            ]
        },
        {
            "M": [
                [
                    5.542537689208984,
                    6.987729549407959
                ],
                [
                    8.086957931518555,
                    5.409036159515381
                ],
                [
                    7.28600549697876,
                    6.5618510246276855
                ],
                [
                    4.635903358459473,
                    5.507058143615723
                ],
                [
                    9.51156234741211,
                    3.094507932662964
                ]
            ],
            "actual_freq": [
                [
                    0.1054,
                    0.6422,
                    0.0437,
                    0.2036,
                    0.0051
                ]
            ],
            "avg_t": 25.0,
            "b": 1.0,
            "freq": [
                [
                    0.1038,
                    0.6592,
                    0.0342,
                    0.2028,
                    0.0
                ]
            ],
            "iter": 69,
            "mse": 0.00040846000000000057,
            "phi1": 0.016860470175743103,
            "phi2": 0.008157414384186268,
            "sig2": 0.9694749142808758,
            "threshold": 25,
            "time": 4.2251811027526855,
            "w": [
                [
                    0.5
                ],
                [
                    0.5
                ]
            ]
        },
        {
            "M": [
                [
                    6.858599662780762,
                    4.349276065826416
                ],
                [
                    4.906883239746094,
                    6.472958564758301
                ],
                [
                    8.900586128234863,
                    4.038076400756836
                ],
                [
                    9.589238166809082,
                    5.026953220367432
                ],
                [
                    8.802274703979492,
                    2.563887357711792
                ]
            ],
            "actual_freq": [
                [
                    0,
                    1,
                    0,
                    0,
                    0
                ]
            ],
            "avg_t": 25.0,
            "b": 10.0,
            "freq": [
                [
                    0.0,
                    0.9953,
                    0.0,
                    0.0,
                    0.0047
                ]
            ],
            "iter": 10,
            "mse": 4.418000000000035e-05,
            "phi1": 0.055701084434986115,
            "phi2": 0.0025344707537442446,
            "sig2": 0.4626726555984523,
            "threshold": 25,
            "time": 0.31453704833984375,
            "w": [
                [
                    0.5
                ],
                [
                    0.5
                ]
            ]
        },
        {
            "M": [
                [
                    7.242189407348633,
                    3.671510934829712
                ],
                [
                    4.111110687255859,
                    9.602066993713379
                ],
                [
                    6.122646808624268,
                    6.926690578460693
                ],
                [
                    4.379148483276367,
                    7.199748516082764
                ],
                [
                    7.287039279937744,
                    5.671372890472412
                ]
            ],
            "actual_freq": [
                [
                    0.9823,
                    0.0,
                    0.0057,
                    0.012,
                    0.0
                ]
            ],
            "avg_t": 25.0,
            "b": 9.0,
            "freq": [
                [
                    0.9734,
                    0.0,
                    0.0,
                    0.0185,
                    0.0081
                ]
            ],
            "iter": 36,
            "mse": 0.00021955999999999834,
            "phi1": 0.014927309937775135,
            "phi2": 0.05903629586100578,
            "sig2": 1.016884389713326,
            "threshold": 25,
            "time": 1.1501579284667969,
            "w": [
                [
                    0.3
                ],
                [
                    0.7
                ]
            ]
        },
        {
            "M": [
                [
                    4.71641731262207,
                    0.6021072864532471
                ],
                [
                    5.175117492675781,
                    5.5599684715271
                ],
                [
                    2.4211277961730957,
                    7.485048294067383
                ],
                [
                    5.189678192138672,
                    7.466696262359619
                ],
                [
                    3.2325780391693115,
                    9.648398399353027
                ]
            ],
            "actual_freq": [
                [
                    0.4089,
                    0.0,
                    0.0012,
                    0.0,
                    0.5899
                ]
            ],
            "avg_t": 25.0,
            "b": 1.0,
            "freq": [
                [
                    0.3992,
                    0.0,
                    0.0019,
                    0.0,
                    0.5989
                ]
            ],
            "iter": 57,
            "mse": 0.0001755799999999999,
            "phi1": 0.0879160687327385,
            "phi2": 0.06413799524307251,
            "sig2": 0.8628091909056798,
            "threshold": 25,
            "time": 1.8745179176330566,
            "w": [
                [
                    0.5
                ],
                [
                    0.5
                ]
            ]
        },
        {
            "M": [
                [
                    6.724548816680908,
                    1.767432451248169
                ],
                [
                    4.699617862701416,
                    3.447458028793335
                ],
                [
                    7.990887641906738,
                    3.64279842376709
                ],
                [
                    2.3675074577331543,
                    6.915092945098877
                ],
                [
                    5.082812786102295,
                    5.804399490356445
                ]
            ],
            "actual_freq": [
                [
                    0.0,
                    0.7317,
                    0.0314,
                    0.2369,
                    0.0
                ]
            ],
            "avg_t": 25.0,
            "b": 9.0,
            "freq": [
                [
                    0.0,
                    0.7438,
                    0.0313,
                    0.2249,
                    0.0
                ]
            ],
            "iter": 76,
            "mse": 0.0002904200000000002,
            "phi1": 0.06422156095504761,
            "phi2": 0.05735572427511215,
            "sig2": 0.5047246732874808,
            "threshold": 25,
            "time": 2.490713119506836,
            "w": [
                [
                    0.5
                ],
                [
                    0.5
                ]
            ]
        },
        {
            "M": [
                [
                    8.890386581420898,
                    4.346701145172119
                ],
                [
                    9.593376159667969,
                    4.078536033630371
                ],
                [
                    8.333658218383789,
                    5.895088195800781
                ],
                [
                    2.8204081058502197,
                    6.120616912841797
                ],
                [
                    1.8572444915771484,
                    5.892374515533447
                ]
            ],
            "actual_freq": [
                [
                    0,
                    0,
                    0,
                    0,
                    1
                ]
            ],
            "avg_t": 25.0,
            "b": 7.0,
            "freq": [
                [
                    0.0047,
                    0.0002,
                    0.0004,
                    0.0039,
                    0.9908
                ]
            ],
            "iter": 56,
            "mse": 0.00012213999999999975,
            "phi1": 0.08220447599887848,
            "phi2": 0.08714669942855835,
            "sig2": 0.5955502078113589,
            "threshold": 25,
            "time": 1.9222419261932373,
            "w": [
                [
                    0.3
                ],
                [
                    0.7
                ]
            ]
        },
        {
            "M": [
                [
                    5.252540111541748,
                    4.838248252868652
                ],
                [
                    4.0265679359436035,
                    4.656548976898193
                ],
                [
                    9.912596702575684,
                    5.388296127319336
                ],
                [
                    5.640157222747803,
                    7.52320671081543
                ],
                [
                    5.378391265869141,
                    2.2073094844818115
                ]
            ],
            "actual_freq": [
                [
                    0.0,
                    0.6172,
                    0.3828,
                    0.0,
                    0.0
                ]
            ],
            "avg_t": 25.0,
            "b": 4.0,
            "freq": [
                [
                    0.0,
                    0.6502,
                    0.3498,
                    0.0,
                    0.0
                ]
            ],
            "iter": 54,
            "mse": 0.0021780000000000002,
            "phi1": 0.02080991119146347,
            "phi2": 0.013817423954606056,
            "sig2": 0.36362971284298695,
            "threshold": 25,
            "time": 1.6112480163574219,
            "w": [
                [
                    0.3
                ],
                [
                    0.7
                ]
            ]
        },
        {
            "M": [
                [
                    3.341033458709717,
                    8.398244857788086
                ],
                [
                    5.128291606903076,
                    5.022617816925049
                ],
                [
                    7.072171688079834,
                    5.400381088256836
                ],
                [
                    3.4222402572631836,
                    2.7541909217834473
                ],
                [
                    6.4407830238342285,
                    7.815905570983887
                ]
            ],
            "actual_freq": [
                [
                    0.166,
                    0.0,
                    0.8259,
                    0.0003,
                    0.0078
                ]
            ],
            "avg_t": 25.0,
            "b": 1.0,
            "freq": [
                [
                    0.1583,
                    0.0103,
                    0.8254,
                    0.0,
                    0.006
                ]
            ],
            "iter": 48,
            "mse": 0.00016896000000000017,
            "phi1": 0.0020139708649367094,
            "phi2": 0.09193044900894165,
            "sig2": 1.0156887271769104,
            "threshold": 25,
            "time": 1.3584489822387695,
            "w": [
                [
                    0.5
                ],
                [
                    0.5
                ]
            ]
        },
        {
            "M": [
                [
                    4.027492046356201,
                    6.302112579345703
                ],
                [
                    5.305212497711182,
                    1.8633898496627808
                ],
                [
                    2.8433618545532227,
                    6.268950462341309
                ],
                [
                    4.269439220428467,
                    0.11362012475728989
                ],
                [
                    4.812302112579346,
                    10.517847061157227
                ]
            ],
            "actual_freq": [
                [
                    0,
                    0,
                    1,
                    0,
                    0
                ]
            ],
            "avg_t": 25.0,
            "b": 14.0,
            "freq": [
                [
                    0.0,
                    0.0,
                    0.9923,
                    0.0077,
                    0.0
                ]
            ],
            "iter": 35,
            "mse": 0.00011858000000000062,
            "phi1": 0.07302908599376678,
            "phi2": 0.06939821690320969,
            "sig2": 1.0885027505944886,
            "threshold": 25,
            "time": 0.9676718711853027,
            "w": [
                [
                    0.7
                ],
                [
                    0.30000000000000004
                ]
            ]
        },
        {
            "M": [
                [
                    3.4142329692840576,
                    6.255743503570557
                ],
                [
                    1.7124286890029907,
                    4.319517135620117
                ],
                [
                    2.3786063194274902,
                    5.583682060241699
                ],
                [
                    5.794674873352051,
                    7.79672908782959
                ],
                [
                    4.537302017211914,
                    8.216238975524902
                ]
            ],
            "actual_freq": [
                [
                    0,
                    0,
                    1,
                    0,
                    0
                ]
            ],
            "avg_t": 25.0,
            "b": 3.0,
            "freq": [
                [
                    0.0,
                    0.0,
                    0.9934,
                    0.0,
                    0.0066
                ]
            ],
            "iter": 5,
            "mse": 8.712000000000066e-05,
            "phi1": 0.0540812723338604,
            "phi2": 0.03054465726017952,
            "sig2": 0.12781900086397438,
            "threshold": 25,
            "time": 0.1428389549255371,
            "w": [
                [
                    0.5
                ],
                [
                    0.5
                ]
            ]
        },
        {
            "M": [
                [
                    7.298882961273193,
                    5.13917350769043
                ],
                [
                    3.936307907104492,
                    8.333329200744629
                ],
                [
                    4.589148044586182,
                    4.0815348625183105
                ],
                [
                    9.08094596862793,
                    8.019296646118164
                ],
                [
                    6.363434314727783,
                    2.814401149749756
                ]
            ],
            "actual_freq": [
                [
                    0,
                    0,
                    0,
                    1,
                    0
                ]
            ],
            "avg_t": 25.0,
            "b": 1.0,
            "freq": [
                [
                    0.0,
                    0.0036,
                    0.0,
                    0.9964,
                    0.0
                ]
            ],
            "iter": 13,
            "mse": 2.592000000000034e-05,
            "phi1": 0.09801923483610153,
            "phi2": 0.004007141105830669,
            "sig2": 0.6691362331026477,
            "threshold": 25,
            "time": 0.4202706813812256,
            "w": [
                [
                    0.3
                ],
                [
                    0.7
                ]
            ]
        },
        {
            "M": [
                [
                    2.5910487174987793,
                    9.118597030639648
                ],
                [
                    1.6624401807785034,
                    5.0573577880859375
                ],
                [
                    8.301371574401855,
                    7.008053779602051
                ],
                [
                    6.94563102722168,
                    6.633464336395264
                ],
                [
                    6.108439922332764,
                    5.870509147644043
                ]
            ],
            "actual_freq": [
                [
                    0,
                    0,
                    0,
                    0,
                    1
                ]
            ],
            "avg_t": 25.0,
            "b": 2.0,
            "freq": [
                [
                    0.0,
                    0.0,
                    0.0,
                    0.0,
                    1.0
                ]
            ],
            "iter": 1,
            "mse": 0.0,
            "phi1": 0.041206054389476776,
            "phi2": 0.06137780472636223,
            "sig2": 0.30553146901909556,
            "threshold": 25,
            "time": 0.032958030700683594,
            "w": [
                [
                    0.7
                ],
                [
                    0.30000000000000004
                ]
            ]
        },
        {
            "M": [
                [
                    2.124112129211426,
                    6.887571334838867
                ],
                [
                    6.021098613739014,
                    6.315555095672607
                ],
                [
                    4.068515777587891,
                    2.8579063415527344
                ],
                [
                    5.47332239151001,
                    2.8654167652130127
                ],
                [
                    6.224741458892822,
                    5.271927356719971
                ]
            ],
            "actual_freq": [
                [
                    0.0,
                    0.8864,
                    0.1136,
                    0.0,
                    0.0
                ]
            ],
            "avg_t": 25.0,
            "b": 10.0,
            "freq": [
                [
                    0.0,
                    0.8888,
                    0.1054,
                    0.0,
                    0.0058
                ]
            ],
            "iter": 49,
            "mse": 0.00010664000000000054,
            "phi1": 0.06848283857107162,
            "phi2": 0.0878816545009613,
            "sig2": 1.0089959274999358,
            "threshold": 25,
            "time": 1.504723072052002,
            "w": [
                [
                    0.5
                ],
                [
                    0.5
                ]
            ]
        },
        {
            "M": [
                [
                    4.453711032867432,
                    3.9663445949554443
                ],
                [
                    2.5472373962402344,
                    7.434571266174316
                ],
                [
                    6.267511367797852,
                    1.8157453536987305
                ],
                [
                    6.477237701416016,
                    3.9176738262176514
                ],
                [
                    4.624317169189453,
                    7.033059597015381
                ]
            ],
            "actual_freq": [
                [
                    0.1468,
                    0.0,
                    0.0,
                    0.8532,
                    0.0
                ]
            ],
            "avg_t": 25.0,
            "b": 2.0,
            "freq": [
                [
                    0.138,
                    0.0,
                    0.0,
                    0.8612,
                    0.0008
                ]
            ],
            "iter": 40,
            "mse": 0.00014208000000000016,
            "phi1": 0.018049776554107666,
            "phi2": 0.02125304937362671,
            "sig2": 0.3730833501525844,
            "threshold": 25,
            "time": 1.2627708911895752,
            "w": [
                [
                    0.5
                ],
                [
                    0.5
                ]
            ]
        },
        {
            "M": [
                [
                    5.919212341308594,
                    2.7811238765716553
                ],
                [
                    10.979934692382812,
                    3.160944938659668
                ],
                [
                    0.0,
                    4.747316837310791
                ],
                [
                    1.4783165454864502,
                    6.845454692840576
                ],
                [
                    5.3917460441589355,
                    6.289735317230225
                ]
            ],
            "actual_freq": [
                [
                    0.0,
                    0.0541,
                    0.6661,
                    0.2798,
                    0.0
                ]
            ],
            "avg_t": 25.0,
            "b": 10.0,
            "freq": [
                [
                    0.0,
                    0.0663,
                    0.6356,
                    0.2981,
                    0.0
                ]
            ],
            "iter": 67,
            "mse": 0.0014139799999999974,
            "phi1": 0.08948307484388351,
            "phi2": 0.08690227568149567,
            "sig2": 0.7716250060073045,
            "threshold": 25,
            "time": 1.846024990081787,
            "w": [
                [
                    0.3
                ],
                [
                    0.7
                ]
            ]
        },
        {
            "M": [
                [
                    3.5305490493774414,
                    3.103564500808716
                ],
                [
                    7.286055564880371,
                    1.6618214845657349
                ],
                [
                    6.026275634765625,
                    5.107762336730957
                ],
                [
                    6.008446216583252,
                    1.4612339735031128
                ],
                [
                    6.7321085929870605,
                    4.9519805908203125
                ]
            ],
            "actual_freq": [
                [
                    0.0,
                    0.2001,
                    0.0,
                    0.7999,
                    0.0
                ]
            ],
            "avg_t": 25.0,
            "b": 11.0,
            "freq": [
                [
                    0.0,
                    0.1772,
                    0.0,
                    0.8228,
                    0.0
                ]
            ],
            "iter": 64,
            "mse": 0.0010488199999999965,
            "phi1": 0.052904561161994934,
            "phi2": 0.06330167502164841,
            "sig2": 0.2649759055216172,
            "threshold": 25,
            "time": 1.7262639999389648,
            "w": [
                [
                    0.3
                ],
                [
                    0.7
                ]
            ]
        },
        {
            "M": [
                [
                    6.245189666748047,
                    4.067928314208984
                ],
                [
                    2.7588090896606445,
                    6.881686687469482
                ],
                [
                    4.268793106079102,
                    7.27308464050293
                ],
                [
                    6.284946918487549,
                    4.422468185424805
                ],
                [
                    2.8665003776550293,
                    7.0307488441467285
                ]
            ],
            "actual_freq": [
                [
                    0.0111,
                    0.0005,
                    0.0063,
                    0.9561,
                    0.026
                ]
            ],
            "avg_t": 25.0,
            "b": 10.0,
            "freq": [
                [
                    0.0199,
                    0.0016,
                    0.0025,
                    0.9514,
                    0.0246
                ]
            ],
            "iter": 90,
            "mse": 0.00011713999999999932,
            "phi1": 0.05708090960979462,
            "phi2": 0.07316216081380844,
            "sig2": 0.7255121897345599,
            "threshold": 25,
            "time": 2.254690170288086,
            "w": [
                [
                    0.3
                ],
                [
                    0.7
                ]
            ]
        },
        {
            "M": [
                [
                    5.86787748336792,
                    4.676967620849609
                ],
                [
                    3.070017099380493,
                    8.781578063964844
                ],
                [
                    4.550523281097412,
                    5.825179576873779
                ],
                [
                    2.1116888523101807,
                    9.073064804077148
                ],
                [
                    7.112280368804932,
                    8.01943302154541
                ]
            ],
            "actual_freq": [
                [
                    0.0,
                    0.0,
                    0.0,
                    0.9913,
                    0.0087
                ]
            ],
            "avg_t": 25.0,
            "b": 1.0,
            "freq": [
                [
                    0.0,
                    0.0,
                    0.0046,
                    0.9911,
                    0.0043
                ]
            ],
            "iter": 82,
            "mse": 4.055999999999999e-05,
            "phi1": 0.005264333449304104,
            "phi2": 0.040632329881191254,
            "sig2": 0.8688007361978054,
            "threshold": 25,
            "time": 2.769155979156494,
            "w": [
                [
                    0.3
                ],
                [
                    0.7
                ]
            ]
        },
        {
            "M": [
                [
                    3.90322208404541,
                    4.625545978546143
                ],
                [
                    6.389569282531738,
                    2.2491791248321533
                ],
                [
                    5.193082809448242,
                    3.54472017288208
                ],
                [
                    6.787064075469971,
                    5.5818257331848145
                ],
                [
                    11.057159423828125,
                    3.3947131633758545
                ]
            ],
            "actual_freq": [
                [
                    0.0,
                    0.0,
                    0.0001,
                    0.3497,
                    0.6502
                ]
            ],
            "avg_t": 25.0,
            "b": 7.0,
            "freq": [
                [
                    0.0,
                    0.0,
                    0.0,
                    0.3372,
                    0.6628
                ]
            ],
            "iter": 97,
            "mse": 0.00031501999999999886,
            "phi1": 0.09733190387487411,
            "phi2": 0.012569612823426723,
            "sig2": 0.8720342759033992,
            "threshold": 25,
            "time": 3.4749138355255127,
            "w": [
                [
                    0.3
                ],
                [
                    0.7
                ]
            ]
        },
        {
            "M": [
                [
                    5.772872447967529,
                    0.0
                ],
                [
                    3.779869556427002,
                    4.787322998046875
                ],
                [
                    0.4991969168186188,
                    5.420650959014893
                ],
                [
                    1.576607584953308,
                    5.639899253845215
                ],
                [
                    3.591665506362915,
                    4.68583345413208
                ]
            ],
            "actual_freq": [
                [
                    0.0,
                    0.0122,
                    0.3732,
                    0.0995,
                    0.5151
                ]
            ],
            "avg_t": 25.0,
            "b": 5.0,
            "freq": [
                [
                    0.0014,
                    0.0213,
                    0.3704,
                    0.1019,
                    0.505
                ]
            ],
            "iter": 143,
            "mse": 0.00020037999999999976,
            "phi1": 0.06738107651472092,
            "phi2": 0.09874749928712845,
            "sig2": 0.7702141698444508,
            "threshold": 25,
            "time": 4.511977910995483,
            "w": [
                [
                    0.3
                ],
                [
                    0.7
                ]
            ]
        },
        {
            "M": [
                [
                    4.336572170257568,
                    2.167266845703125
                ],
                [
                    3.9289956092834473,
                    5.322112560272217
                ],
                [
                    4.489082336425781,
                    6.0833845138549805
                ],
                [
                    3.7144343852996826,
                    3.6737751960754395
                ],
                [
                    0.19123665988445282,
                    6.9318366050720215
                ]
            ],
            "actual_freq": [
                [
                    0.0,
                    0.9801,
                    0.016,
                    0.0,
                    0.0039
                ]
            ],
            "avg_t": 25.0,
            "b": 8.0,
            "freq": [
                [
                    0.0,
                    0.982,
                    0.0151,
                    0.0,
                    0.0029
                ]
            ],
            "iter": 33,
            "mse": 5.420000000000048e-06,
            "phi1": 0.06691499799489975,
            "phi2": 0.04718727245926857,
            "sig2": 1.021647049589594,
            "threshold": 25,
            "time": 1.1454761028289795,
            "w": [
                [
                    0.5
                ],
                [
                    0.5
                ]
            ]
        },
        {
            "M": [
                [
                    1.0676240921020508,
                    5.48311710357666
                ],
                [
                    6.425516605377197,
                    5.641823768615723
                ],
                [
                    2.0705056190490723,
                    8.853982925415039
                ],
                [
                    1.8843114376068115,
                    7.3558478355407715
                ],
                [
                    7.670456409454346,
                    4.609539031982422
                ]
            ],
            "actual_freq": [
                [
                    0.0621,
                    0.0,
                    0.0005,
                    0.8483,
                    0.0891
                ]
            ],
            "avg_t": 25.0,
            "b": 7.0,
            "freq": [
                [
                    0.0621,
                    0.0,
                    0.0006,
                    0.8596,
                    0.0777
                ]
            ],
            "iter": 87,
            "mse": 0.0002576599999999993,
            "phi1": 0.09977684170007706,
            "phi2": 0.060328688472509384,
            "sig2": 1.0667729178017917,
            "threshold": 25,
            "time": 2.805475950241089,
            "w": [
                [
                    0.3
                ],
                [
                    0.7
                ]
            ]
        },
        {
            "M": [
                [
                    7.137906074523926,
                    6.390215873718262
                ],
                [
                    0.2419736683368683,
                    7.852108478546143
                ],
                [
                    8.3966064453125,
                    5.43067741394043
                ],
                [
                    7.699975967407227,
                    3.7284486293792725
                ],
                [
                    5.581864356994629,
                    4.646358966827393
                ]
            ],
            "actual_freq": [
                [
                    0.9851,
                    0.0,
                    0.0,
                    0.0149,
                    0.0
                ]
            ],
            "avg_t": 25.0,
            "b": 12.0,
            "freq": [
                [
                    0.9959,
                    0.0,
                    0.0038,
                    0.0003,
                    0.0
                ]
            ],
            "iter": 66,
            "mse": 0.00034424000000000065,
            "phi1": 0.0021145015489310026,
            "phi2": 0.06350748986005783,
            "sig2": 0.26371249208698144,
            "threshold": 25,
            "time": 4.357512950897217,
            "w": [
                [
                    0.7
                ],
                [
                    0.30000000000000004
                ]
            ]
        },
        {
            "M": [
                [
                    4.79153299331665,
                    5.716303825378418
                ],
                [
                    4.755220890045166,
                    5.761855125427246
                ],
                [
                    6.558867931365967,
                    2.7424709796905518
                ],
                [
                    2.4220468997955322,
                    8.789827346801758
                ],
                [
                    4.865455627441406,
                    6.851506233215332
                ]
            ],
            "actual_freq": [
                [
                    0.0,
                    0.4153,
                    0.5847,
                    0.0,
                    0.0
                ]
            ],
            "avg_t": 25.0,
            "b": 1.0,
            "freq": [
                [
                    0.0,
                    0.3981,
                    0.6005,
                    0.0014,
                    0.0
                ]
            ],
            "iter": 10,
            "mse": 0.0005474400000000009,
            "phi1": 0.03675491362810135,
            "phi2": 0.05208766460418701,
            "sig2": 0.10262079674354754,
            "threshold": 25,
            "time": 0.2878568172454834,
            "w": [
                [
                    0.7
                ],
                [
                    0.30000000000000004
                ]
            ]
        },
        {
            "M": [
                [
                    5.663613319396973,
                    0.0
                ],
                [
                    2.9049105644226074,
                    7.7200798988342285
                ],
                [
                    3.8329882621765137,
                    3.376272678375244
                ],
                [
                    5.4428510665893555,
                    6.541003704071045
                ],
                [
                    5.564013957977295,
                    2.380197048187256
                ]
            ],
            "actual_freq": [
                [
                    0.9787,
                    0.0,
                    0.0,
                    0.0,
                    0.0213
                ]
            ],
            "avg_t": 25.0,
            "b": 4.0,
            "freq": [
                [
                    0.9796,
                    0.0002,
                    0.0,
                    0.0,
                    0.0202
                ]
            ],
            "iter": 77,
            "mse": 2.060000000000022e-06,
            "phi1": 0.027095889672636986,
            "phi2": 0.07039701193571091,
            "sig2": 0.15345322331086467,
            "threshold": 25,
            "time": 2.7402420043945312,
            "w": [
                [
                    0.7
                ],
                [
                    0.30000000000000004
                ]
            ]
        },
        {
            "M": [
                [
                    4.315163612365723,
                    4.769348621368408
                ],
                [
                    0.35229790210723877,
                    0.002579402644187212
                ],
                [
                    4.951016902923584,
                    5.628548622131348
                ],
                [
                    5.572818756103516,
                    3.1566250324249268
                ],
                [
                    5.779648780822754,
                    4.8853864669799805
                ]
            ],
            "actual_freq": [
                [
                    0.7392,
                    0.0,
                    0.2134,
                    0.0006,
                    0.0468
                ]
            ],
            "avg_t": 25.0,
            "b": 1.0,
            "freq": [
                [
                    0.7653,
                    0.0,
                    0.1932,
                    0.0,
                    0.0415
                ]
            ],
            "iter": 102,
            "mse": 0.0011177000000000003,
            "phi1": 0.07176976650953293,
            "phi2": 0.059316523373126984,
            "sig2": 0.7588545913134521,
            "threshold": 25,
            "time": 3.0422208309173584,
            "w": [
                [
                    0.7
                ],
                [
                    0.30000000000000004
                ]
            ]
        },
        {
            "M": [
                [
                    9.707995414733887,
                    2.0774481296539307
                ],
                [
                    4.853289604187012,
                    5.147969722747803
                ],
                [
                    8.860234260559082,
                    4.071352481842041
                ],
                [
                    6.911315441131592,
                    5.451418399810791
                ],
                [
                    8.96835708618164,
                    3.901407480239868
                ]
            ],
            "actual_freq": [
                [
                    0.0025,
                    0.3196,
                    0.3376,
                    0.2367,
                    0.1036
                ]
            ],
            "avg_t": 25.0,
            "b": 5.0,
            "freq": [
                [
                    0.0006,
                    0.3701,
                    0.3226,
                    0.2211,
                    0.0856
                ]
            ],
            "iter": 135,
            "mse": 0.0033462199999999996,
            "phi1": 0.050021376460790634,
            "phi2": 0.09677702933549881,
            "sig2": 0.9578853003761181,
            "threshold": 25,
            "time": 4.344954967498779,
            "w": [
                [
                    0.5
                ],
                [
                    0.5
                ]
            ]
        },
        {
            "M": [
                [
                    2.8368356227874756,
                    1.8393723964691162
                ],
                [
                    0.0,
                    6.188703536987305
                ],
                [
                    6.534334182739258,
                    2.1179511547088623
                ],
                [
                    6.444489479064941,
                    5.5732197761535645
                ],
                [
                    3.0791327953338623,
                    3.872131109237671
                ]
            ],
            "actual_freq": [
                [
                    0.0,
                    0.0,
                    0.9988,
                    0.0012,
                    0.0
                ]
            ],
            "avg_t": 25.0,
            "b": 2.0,
            "freq": [
                [
                    0.0,
                    0.0,
                    0.9916,
                    0.0,
                    0.0084
                ]
            ],
            "iter": 61,
            "mse": 0.00012383999999999976,
            "phi1": 0.04639233276247978,
            "phi2": 0.0015005598543211818,
            "sig2": 0.686615512997551,
            "threshold": 25,
            "time": 2.4040300846099854,
            "w": [
                [
                    0.3
                ],
                [
                    0.7
                ]
            ]
        },
        {
            "M": [
                [
                    0.0,
                    5.010509490966797
                ],
                [
                    6.78999662399292,
                    4.628995418548584
                ],
                [
                    6.030508995056152,
                    3.213893413543701
                ],
                [
                    0.0,
                    5.104160308837891
                ],
                [
                    5.316041469573975,
                    4.51744270324707
                ]
            ],
            "actual_freq": [
                [
                    0.0,
                    0.0,
                    0.946,
                    0.0429,
                    0.0111
                ]
            ],
            "avg_t": 25.0,
            "b": 10.0,
            "freq": [
                [
                    0.0,
                    0.0017,
                    0.9474,
                    0.0461,
                    0.0048
                ]
            ],
            "iter": 67,
            "mse": 5.478000000000022e-05,
            "phi1": 0.07839557528495789,
            "phi2": 0.009424219839274883,
            "sig2": 0.9722173519740797,
            "threshold": 25,
            "time": 2.101861000061035,
            "w": [
                [
                    0.3
                ],
                [
                    0.7
                ]
            ]
        },
        {
            "M": [
                [
                    6.387080192565918,
                    6.754040241241455
                ],
                [
                    8.65134334564209,
                    5.153200149536133
                ],
                [
                    4.708312511444092,
                    2.439549446105957
                ],
                [
                    4.180342674255371,
                    6.428487300872803
                ],
                [
                    6.338053226470947,
                    6.23899507522583
                ]
            ],
            "actual_freq": [
                [
                    0.0,
                    0.1397,
                    0.0,
                    0.0061,
                    0.8542
                ]
            ],
            "avg_t": 25.0,
            "b": 5.0,
            "freq": [
                [
                    0.0,
                    0.1537,
                    0.0,
                    0.0002,
                    0.8461
                ]
            ],
            "iter": 73,
            "mse": 0.00029642000000000026,
            "phi1": 0.09701666235923767,
            "phi2": 0.017238494008779526,
            "sig2": 0.5077329922246233,
            "threshold": 25,
            "time": 1.9160521030426025,
            "w": [
                [
                    0.5
                ],
                [
                    0.5
                ]
            ]
        },
        {
            "M": [
                [
                    3.8593926429748535,
                    1.275490641593933
                ],
                [
                    4.816190242767334,
                    4.640552997589111
                ],
                [
                    5.003805637359619,
                    6.372490882873535
                ],
                [
                    4.830221652984619,
                    4.6113128662109375
                ],
                [
                    4.124161243438721,
                    9.229902267456055
                ]
            ],
            "actual_freq": [
                [
                    0.6899,
                    0.0,
                    0.0,
                    0.0,
                    0.3101
                ]
            ],
            "avg_t": 25.0,
            "b": 6.0,
            "freq": [
                [
                    0.7107,
                    0.0,
                    0.0002,
                    0.0002,
                    0.2889
                ]
            ],
            "iter": 66,
            "mse": 0.0008821600000000015,
            "phi1": 0.014488618820905685,
            "phi2": 0.07717712223529816,
            "sig2": 0.3690876237201882,
            "threshold": 25,
            "time": 1.9112060070037842,
            "w": [
                [
                    0.7
                ],
                [
                    0.30000000000000004
                ]
            ]
        },
        {
            "M": [
                [
                    2.594912052154541,
                    5.934741497039795
                ],
                [
                    3.220858097076416,
                    5.141543865203857
                ],
                [
                    4.624067783355713,
                    5.202241897583008
                ],
                [
                    4.388510704040527,
                    5.7774882316589355
                ],
                [
                    3.361077308654785,
                    5.5658650398254395
                ]
            ],
            "actual_freq": [
                [
                    0.0128,
                    0.9643,
                    0.0006,
                    0.0223,
                    0.0
                ]
            ],
            "avg_t": 25.0,
            "b": 14.0,
            "freq": [
                [
                    0.0026,
                    0.9668,
                    0.0,
                    0.0299,
                    0.0007
                ]
            ],
            "iter": 150,
            "mse": 0.00016889999999999974,
            "phi1": 0.043460551649332047,
            "phi2": 0.06596971303224564,
            "sig2": 0.15355324797928974,
            "threshold": 25,
            "time": 4.258121967315674,
            "w": [
                [
                    0.5
                ],
                [
                    0.5
                ]
            ]
        },
        {
            "M": [
                [
                    6.668105602264404,
                    5.321040153503418
                ],
                [
                    6.565345764160156,
                    5.380595684051514
                ],
                [
                    8.092421531677246,
                    2.184122323989868
                ],
                [
                    6.278852939605713,
                    0.0
                ],
                [
                    5.291715621948242,
                    7.5667548179626465
                ]
            ],
            "actual_freq": [
                [
                    0,
                    0,
                    0,
                    1,
                    0
                ]
            ],
            "avg_t": 25.0,
            "b": 1.0,
            "freq": [
                [
                    0.0035,
                    0.0,
                    0.002,
                    0.9942,
                    0.0003
                ]
            ],
            "iter": 50,
            "mse": 4.998000000000032e-05,
            "phi1": 0.09381768852472305,
            "phi2": 0.012290721759200096,
            "sig2": 1.0513359898341836,
            "threshold": 25,
            "time": 1.4670860767364502,
            "w": [
                [
                    0.3
                ],
                [
                    0.7
                ]
            ]
        },
        {
            "M": [
                [
                    2.7172579765319824,
                    8.5379056930542
                ],
                [
                    3.0366103649139404,
                    5.972978115081787
                ],
                [
                    2.3869986534118652,
                    9.542302131652832
                ],
                [
                    2.307056188583374,
                    1.871577501296997
                ],
                [
                    4.071183204650879,
                    8.474492073059082
                ]
            ],
            "actual_freq": [
                [
                    0.9961,
                    0.0013,
                    0.0,
                    0.0026,
                    0.0
                ]
            ],
            "avg_t": 25.0,
            "b": 3.0,
            "freq": [
                [
                    0.9936,
                    0.0,
                    0.0,
                    0.0064,
                    0.0
                ]
            ],
            "iter": 6,
            "mse": 2.2379999999999738e-05,
            "phi1": 0.06339827179908752,
            "phi2": 0.08570467680692673,
            "sig2": 0.6625289728772197,
            "threshold": 25,
            "time": 0.1484389305114746,
            "w": [
                [
                    0.7
                ],
                [
                    0.30000000000000004
                ]
            ]
        },
        {
            "M": [
                [
                    3.8737971782684326,
                    6.042056083679199
                ],
                [
                    5.678450584411621,
                    7.711346626281738
                ],
                [
                    6.678833961486816,
                    2.3052566051483154
                ],
                [
                    2.494399309158325,
                    7.709856033325195
                ],
                [
                    5.423279762268066,
                    5.332045078277588
                ]
            ],
            "actual_freq": [
                [
                    0.998,
                    0.0,
                    0.0,
                    0.0015,
                    0.0005
                ]
            ],
            "avg_t": 25.0,
            "b": 13.0,
            "freq": [
                [
                    0.997,
                    0.003,
                    0.0,
                    0.0,
                    0.0
                ]
            ],
            "iter": 41,
            "mse": 1.2500000000000002e-05,
            "phi1": 0.05330462008714676,
            "phi2": 0.03854947164654732,
            "sig2": 0.6964903744821775,
            "threshold": 25,
            "time": 1.194101095199585,
            "w": [
                [
                    0.3
                ],
                [
                    0.7
                ]
            ]
        },
        {
            "M": [
                [
                    4.31442403793335,
                    3.8986480236053467
                ],
                [
                    4.516874313354492,
                    6.509978771209717
                ],
                [
                    5.52895975112915,
                    4.778088092803955
                ],
                [
                    8.721394538879395,
                    2.73302960395813
                ],
                [
                    5.857426643371582,
                    6.766371250152588
                ]
            ],
            "actual_freq": [
                [
                    0.1438,
                    0.8558,
                    0.0004,
                    0.0,
                    0.0
                ]
            ],
            "avg_t": 25.0,
            "b": 14.0,
            "freq": [
                [
                    0.1361,
                    0.8636,
                    0.0,
                    0.0003,
                    0.0
                ]
            ],
            "iter": 117,
            "mse": 0.00012038000000000065,
            "phi1": 0.0365435965359211,
            "phi2": 0.041625551879405975,
            "sig2": 1.0477654089361392,
            "threshold": 25,
            "time": 3.1416289806365967,
            "w": [
                [
                    0.7
                ],
                [
                    0.30000000000000004
                ]
            ]
        },
        {
            "M": [
                [
                    3.647357940673828,
                    5.031890869140625
                ],
                [
                    5.092048645019531,
                    0.0
                ],
                [
                    3.1442267894744873,
                    5.591548442840576
                ],
                [
                    3.4106252193450928,
                    5.289278030395508
                ],
                [
                    1.6330127716064453,
                    7.885232448577881
                ]
            ],
            "actual_freq": [
                [
                    0.0453,
                    0.13,
                    0.0,
                    0.8121,
                    0.0126
                ]
            ],
            "avg_t": 25.0,
            "b": 4.0,
            "freq": [
                [
                    0.0453,
                    0.1304,
                    0.0069,
                    0.8049,
                    0.0125
                ]
            ],
            "iter": 117,
            "mse": 9.962000000000135e-05,
            "phi1": 0.03848390281200409,
            "phi2": 0.0694032534956932,
            "sig2": 0.29558855883810276,
            "threshold": 25,
            "time": 3.1807501316070557,
            "w": [
                [
                    0.5
                ],
                [
                    0.5
                ]
            ]
        },
        {
            "M": [
                [
                    2.3824636936187744,
                    1.5431733131408691
                ],
                [
                    4.7955827713012695,
                    3.2517290115356445
                ],
                [
                    1.6627650260925293,
                    5.8596673011779785
                ],
                [
                    0.7113504409790039,
                    3.9131619930267334
                ],
                [
                    1.3581124544143677,
                    2.959176778793335
                ]
            ],
            "actual_freq": [
                [
                    0.0525,
                    0.9475,
                    0.0,
                    0.0,
                    0.0
                ]
            ],
            "avg_t": 25.0,
            "b": 2.0,
            "freq": [
                [
                    0.0595,
                    0.9405,
                    0.0,
                    0.0,
                    0.0
                ]
            ],
            "iter": 46,
            "mse": 9.800000000000008e-05,
            "phi1": 0.018834484741091728,
            "phi2": 0.022476017475128174,
            "sig2": 0.6096881698003898,
            "threshold": 25,
            "time": 1.1236522197723389,
            "w": [
                [
                    0.3
                ],
                [
                    0.7
                ]
            ]
        },
        {
            "M": [
                [
                    7.062967777252197,
                    3.016019582748413
                ],
                [
                    6.2690205574035645,
                    4.593209266662598
                ],
                [
                    0.14763957262039185,
                    4.160488128662109
                ],
                [
                    8.31791877746582,
                    3.6227805614471436
                ],
                [
                    3.0153751373291016,
                    5.976137638092041
                ]
            ],
            "actual_freq": [
                [
                    0.1629,
                    0.0,
                    0.0,
                    0.4882,
                    0.3489
                ]
            ],
            "avg_t": 25.0,
            "b": 13.0,
            "freq": [
                [
                    0.1686,
                    0.0,
                    0.0,
                    0.4675,
                    0.3639
                ]
            ],
            "iter": 139,
            "mse": 0.0006859800000000004,
            "phi1": 0.08030667155981064,
            "phi2": 0.07828627526760101,
            "sig2": 0.5822435264005867,
            "threshold": 25,
            "time": 3.9600188732147217,
            "w": [
                [
                    0.3
                ],
                [
                    0.7
                ]
            ]
        },
        {
            "M": [
                [
                    5.796267986297607,
                    0.0914163589477539
                ],
                [
                    2.82519268989563,
                    7.093227863311768
                ],
                [
                    2.7559797763824463,
                    2.722102642059326
                ],
                [
                    3.768857717514038,
                    2.662748098373413
                ],
                [
                    5.010804176330566,
                    12.518939971923828
                ]
            ],
            "actual_freq": [
                [
                    0,
                    0,
                    1,
                    0,
                    0
                ]
            ],
            "avg_t": 25.0,
            "b": 15.0,
            "freq": [
                [
                    0.0,
                    0.008,
                    0.992,
                    0.0,
                    0.0
                ]
            ],
            "iter": 73,
            "mse": 0.00012800000000000013,
            "phi1": 0.08815643191337585,
            "phi2": 0.09736129641532898,
            "sig2": 0.6096680875877738,
            "threshold": 25,
            "time": 1.9888291358947754,
            "w": [
                [
                    0.7
                ],
                [
                    0.30000000000000004
                ]
            ]
        },
        {
            "M": [
                [
                    4.351649761199951,
                    2.4903693199157715
                ],
                [
                    1.5026147365570068,
                    6.243762016296387
                ],
                [
                    4.964601516723633,
                    4.739288330078125
                ],
                [
                    5.381866455078125,
                    0.22759637236595154
                ],
                [
                    4.6169586181640625,
                    10.290262222290039
                ]
            ],
            "actual_freq": [
                [
                    0.0009,
                    0.9991,
                    0.0,
                    0.0,
                    0.0
                ]
            ],
            "avg_t": 25.0,
            "b": 10.0,
            "freq": [
                [
                    0.0053,
                    0.99,
                    0.0047,
                    0.0,
                    0.0
                ]
            ],
            "iter": 32,
            "mse": 0.00012425999999999995,
            "phi1": 0.05025651305913925,
            "phi2": 0.03474269434809685,
            "sig2": 0.9704614106787908,
            "threshold": 25,
            "time": 0.8863670825958252,
            "w": [
                [
                    0.7
                ],
                [
                    0.30000000000000004
                ]
            ]
        },
        {
            "M": [
                [
                    2.189342498779297,
                    3.806583881378174
                ],
                [
                    2.814554452896118,
                    2.0961644649505615
                ],
                [
                    2.9214258193969727,
                    3.806025266647339
                ],
                [
                    1.8798747062683105,
                    2.3428359031677246
                ],
                [
                    6.662611484527588,
                    3.441300630569458
                ]
            ],
            "actual_freq": [
                [
                    0.0,
                    0.0,
                    0.9994,
                    0.0006,
                    0.0
                ]
            ],
            "avg_t": 25.0,
            "b": 9.0,
            "freq": [
                [
                    0.0,
                    0.0018,
                    0.9946,
                    0.0036,
                    0.0
                ]
            ],
            "iter": 46,
            "mse": 3.527999999999919e-05,
            "phi1": 0.03054189868271351,
            "phi2": 0.08604814857244492,
            "sig2": 0.26045370625114195,
            "threshold": 25,
            "time": 1.357630968093872,
            "w": [
                [
                    0.3
                ],
                [
                    0.7
                ]
            ]
        },
        {
            "M": [
                [
                    9.459015846252441,
                    1.997849941253662
                ],
                [
                    5.6904754638671875,
                    3.736875057220459
                ],
                [
                    1.5305505990982056,
                    7.364466190338135
                ],
                [
                    7.165966510772705,
                    9.01108169555664
                ],
                [
                    2.214104175567627,
                    4.641304969787598
                ]
            ],
            "actual_freq": [
                [
                    0,
                    0,
                    0,
                    0,
                    1
                ]
            ],
            "avg_t": 25.0,
            "b": 2.0,
            "freq": [
                [
                    0.0,
                    0.0,
                    0.0,
                    0.0,
                    1.0
                ]
            ],
            "iter": 1,
            "mse": 0.0,
            "phi1": 0.05707841366529465,
            "phi2": 0.07498341798782349,
            "sig2": 0.9748304236948585,
            "threshold": 25,
            "time": 0.024834871292114258,
            "w": [
                [
                    0.3
                ],
                [
                    0.7
                ]
            ]
        },
        {
            "M": [
                [
                    5.680351257324219,
                    2.3720691204071045
                ],
                [
                    4.0914154052734375,
                    5.8848066329956055
                ],
                [
                    5.693081378936768,
                    2.759768009185791
                ],
                [
                    3.9797585010528564,
                    4.9962263107299805
                ],
                [
                    3.9730536937713623,
                    8.153871536254883
                ]
            ],
            "actual_freq": [
                [
                    0,
                    0,
                    0,
                    0,
                    1
                ]
            ],
            "avg_t": 25.0,
            "b": 2.0,
            "freq": [
                [
                    0.0026,
                    0.0,
                    0.0077,
                    0.0007,
                    0.989
                ]
            ],
            "iter": 44,
            "mse": 0.00018754000000000023,
            "phi1": 0.09762059897184372,
            "phi2": 0.010284041054546833,
            "sig2": 0.8251273660811714,
            "threshold": 25,
            "time": 1.2973928451538086,
            "w": [
                [
                    0.5
                ],
                [
                    0.5
                ]
            ]
        },
        {
            "M": [
                [
                    7.008079528808594,
                    1.3885232210159302
                ],
                [
                    1.8610197305679321,
                    7.992697715759277
                ],
                [
                    7.652758598327637,
                    5.735329627990723
                ],
                [
                    6.52637243270874,
                    5.827419281005859
                ],
                [
                    3.145883321762085,
                    5.6456828117370605
                ]
            ],
            "actual_freq": [
                [
                    0.0011,
                    0.0,
                    0.0,
                    0.0003,
                    0.9986
                ]
            ],
            "avg_t": 25.0,
            "b": 4.0,
            "freq": [
                [
                    0.0088,
                    0.0005,
                    0.0,
                    0.0,
                    0.9907
                ]
            ],
            "iter": 19,
            "mse": 0.00012204000000000029,
            "phi1": 0.04240047559142113,
            "phi2": 0.026969105005264282,
            "sig2": 1.061369876979517,
            "threshold": 25,
            "time": 0.634774923324585,
            "w": [
                [
                    0.7
                ],
                [
                    0.30000000000000004
                ]
            ]
        },
        {
            "M": [
                [
                    3.3074049949645996,
                    4.673415660858154
                ],
                [
                    7.8935933113098145,
                    5.41964864730835
                ],
                [
                    2.402010679244995,
                    6.148293972015381
                ],
                [
                    3.9699349403381348,
                    6.549685478210449
                ],
                [
                    3.2535781860351562,
                    6.782481670379639
                ]
            ],
            "actual_freq": [
                [
                    0.9872,
                    0.0,
                    0.0,
                    0.0,
                    0.0128
                ]
            ],
            "avg_t": 25.0,
            "b": 7.0,
            "freq": [
                [
                    0.9865,
                    0.0031,
                    0.0,
                    0.0059,
                    0.0045
                ]
            ],
            "iter": 93,
            "mse": 0.00011379999999999992,
            "phi1": 0.022040801122784615,
            "phi2": 0.09350147098302841,
            "sig2": 0.414712104841493,
            "threshold": 25,
            "time": 2.550650119781494,
            "w": [
                [
                    0.5
                ],
                [
                    0.5
                ]
            ]
        },
        {
            "M": [
                [
                    1.5043206214904785,
                    7.547373294830322
                ],
                [
                    1.146628975868225,
                    0.8983203172683716
                ],
                [
                    0.23171314597129822,
                    8.188950538635254
                ],
                [
                    9.776695251464844,
                    7.154189109802246
                ],
                [
                    7.6890549659729,
                    6.041090488433838
                ]
            ],
            "actual_freq": [
                [
                    0.9995,
                    0.0,
                    0.0,
                    0.0,
                    0.0005
                ]
            ],
            "avg_t": 25.0,
            "b": 2.0,
            "freq": [
                [
                    0.9927,
                    0.0073,
                    0.0,
                    0.0,
                    0.0
                ]
            ],
            "iter": 22,
            "mse": 9.978000000000039e-05,
            "phi1": 0.052677400410175323,
            "phi2": 0.007905324921011925,
            "sig2": 0.34188790187071594,
            "threshold": 25,
            "time": 0.6660220623016357,
            "w": [
                [
                    0.3
                ],
                [
                    0.7
                ]
            ]
        },
        {
            "M": [
                [
                    7.547977924346924,
                    8.101462364196777
                ],
                [
                    5.075254917144775,
                    9.493560791015625
                ],
                [
                    0.0,
                    0.0
                ],
                [
                    7.559548377990723,
                    8.29432487487793
                ],
                [
                    6.000149250030518,
                    10.185593605041504
                ]
            ],
            "actual_freq": [
                [
                    0.0,
                    0.0812,
                    0.0,
                    0.9185,
                    0.0003
                ]
            ],
            "avg_t": 25.0,
            "b": 14.0,
            "freq": [
                [
                    0.0,
                    0.0639,
                    0.003,
                    0.9299,
                    0.0032
                ]
            ],
            "iter": 116,
            "mse": 0.00044665999999999906,
            "phi1": 0.01598278433084488,
            "phi2": 0.07209550589323044,
            "sig2": 0.9039427399901485,
            "threshold": 25,
            "time": 4.071099042892456,
            "w": [
                [
                    0.3
                ],
                [
                    0.7
                ]
            ]
        },
        {
            "M": [
                [
                    6.867576599121094,
                    0.1289176046848297
                ],
                [
                    5.789748191833496,
                    7.644302845001221
                ],
                [
                    6.5603928565979,
                    4.374823570251465
                ],
                [
                    4.468069076538086,
                    7.7130656242370605
                ],
                [
                    4.183436393737793,
                    8.610163688659668
                ]
            ],
            "actual_freq": [
                [
                    0.1782,
                    0.0,
                    0.8022,
                    0.0043,
                    0.0153
                ]
            ],
            "avg_t": 25.0,
            "b": 4.0,
            "freq": [
                [
                    0.1796,
                    0.0003,
                    0.8113,
                    0.0004,
                    0.0084
                ]
            ],
            "iter": 94,
            "mse": 0.00014767999999999997,
            "phi1": 0.07574588060379028,
            "phi2": 0.09979049861431122,
            "sig2": 0.7030947796565529,
            "threshold": 25,
            "time": 3.025169849395752,
            "w": [
                [
                    0.5
                ],
                [
                    0.5
                ]
            ]
        }
    ]
}